spexwavepy/__init__.py
spexwavepy/corefun.py
spexwavepy/imstackfun.py
spexwavepy/postfun.py
spexwavepy/trackfun.py
spexwavepy-1.0.1.dist-info/LICENSE
spexwavepy-1.0.1.dist-info/METADATA
spexwavepy-1.0.1.dist-info/WHEEL
spexwavepy-1.0.1.dist-info/top_level.txt
spexwavepy-1.0.1.dist-info/RECORD
