Metadata-Version: 2.1
Name: spexwavepy
Version: 1.0.1
Summary: Spexwavepy is an open-source Python package dedicated to the speckle-based wavefront sensing techniques for X-ray optics.
Author-email: Lingfei Hu <hulf88@ustc.edu.cn>, Hongchang Wang <hongchang.wang@diamond.ac.uk>
License: Apache License
Keywords: Synchrotron Radiation,Free Electron Laser,X-ray,Wavefront Sensing,Speckle
Classifier: License :: OSI Approved :: Apache Software License
Classifier: Programming Language :: Python
Classifier: Programming Language :: Python :: 3
License-File: LICENSE
Requires-Dist: numpy
Requires-Dist: scipy
Requires-Dist: opencv-python >=4.4
Requires-Dist: natsort >=8.1.0
